[{"start":{"id":"70401"},"end":{"id":"70402"},"type":"arrow","endArrowhead":"triangle","x":1040.4554,"y":374.47684,"width":-25.910816,"height":111.04635,"backgroundColor":"#FFFFFF","strokeColor":"#F33E94","label":{"text":"50%\r\n达成1:旗舰为航母\r\n","fontSize":12,"strokeColor":"#000000"},"id":"70401:70402"},{"start":{"id":"70401"},"end":{"id":"70403"},"type":"arrow","endArrowhead":"triangle","x":1028.9288,"y":343.09546,"width":-102.85771,"height":-76.190895,"backgroundColor":"#FFFFFF","strokeColor":"#F33E94","label":{"text":"50%\r\n达成1:重巡≥2\r\n","fontSize":12,"strokeColor":"#000000"},"id":"70401:70403"},{"start":{"id":"70402"},"end":{"id":"70404"},"type":"arrow","endArrowhead":"triangle","x":998,"y":521,"width":-66,"height":88,"backgroundColor":"#FFFFFF","strokeColor":"#B394F3","label":{"text":"","fontSize":12,"strokeColor":"#000000"},"id":"70402:70404"},{"start":{"id":"70404"},"end":{"id":"70405"},"type":"arrow","endArrowhead":"triangle","x":906.2451,"y":610.48096,"width":-152.49022,"height":-160.96188,"backgroundColor":"#FFFFFF","strokeColor":"#94F8F3","label":{"text":"75%\r\n","fontSize":12,"strokeColor":"#000000"},"id":"70404:70405"},{"start":{"id":"70404"},"end":{"id":"70407"},"type":"arrow","endArrowhead":"triangle","x":903.5819,"y":636.42126,"width":-82.163795,"height":57.15742,"backgroundColor":"#FFFFFF","strokeColor":"#94F8F3","label":{"text":"25%\r\n达成1:装母≥1\r\n","fontSize":12,"strokeColor":"#000000"},"id":"70404:70407"},{"start":{"id":"70405"},"end":{"id":"70403"},"type":"arrow","endArrowhead":"triangle","x":753.7325,"y":420.45975,"width":142.53506,"height":-150.91948,"backgroundColor":"#FFFFFF","strokeColor":"#F394D6","label":{"text":"25%\r\n\n击破:-0D:开启","fontSize":12,"strokeColor":"#000000"},"id":"70405:70403"},{"start":{"id":"70405"},"end":{"id":"70408"},"type":"arrow","endArrowhead":"triangle","x":720.0073,"y":434.45966,"width":-145.0146,"height":-3.9193134,"backgroundColor":"#FFFFFF","strokeColor":"#F394D6","label":{"text":"75%\r\n","fontSize":12,"strokeColor":"#000000"},"id":"70405:70408"},{"start":{"id":"70403"},"end":{"id":"70406"},"type":"arrow","endArrowhead":"triangle","x":890.26135,"y":258.22263,"width":-205.52269,"height":33.554726,"backgroundColor":"#FFFFFF","strokeColor":"#F3943E","label":{"text":"","fontSize":12,"strokeColor":"#000000"},"id":"70403:70406"},{"start":{"id":"70406"},"end":{"id":"70405"},"type":"arrow","endArrowhead":"triangle","x":674.44446,"y":312.6296,"width":56.111145,"height":104.7408,"backgroundColor":"#FFFFFF","strokeColor":"#F30994","label":{"text":"","fontSize":12,"strokeColor":"#000000"},"id":"70406:70405"},{"start":{"id":"70408"},"end":{"id":"70406"},"type":"arrow","endArrowhead":"triangle","x":567.6335,"y":414.4953,"width":84.733086,"height":-103.9906,"backgroundColor":"#FFFFFF","strokeColor":"#9403F3","label":{"text":"33%\r\n\n击破:-0D:开启","fontSize":12,"strokeColor":"#000000"},"id":"70408:70406"},{"start":{"id":"70408"},"end":{"id":"70412"},"type":"arrow","endArrowhead":"triangle","x":544.02686,"y":446.72095,"width":-83.05374,"height":126.55808,"backgroundColor":"#FFFFFF","strokeColor":"#9403F3","label":{"text":"22%\r\n达成1:战巡≥2\r\n","fontSize":12,"strokeColor":"#000000"},"id":"70408:70412"},{"start":{"id":"70408"},"end":{"id":"70413"},"type":"arrow","endArrowhead":"triangle","x":537.46375,"y":420.38336,"width":-119.927505,"height":-65.76669,"backgroundColor":"#FFFFFF","strokeColor":"#9403F3","label":{"text":"44%\r\n\n击破:-0J:关闭","fontSize":12,"strokeColor":"#000000"},"id":"70408:70413"},{"start":{"id":"70412"},"end":{"id":"70411"},"type":"arrow","endArrowhead":"triangle","x":460.67987,"y":606.9098,"width":38.64028,"height":61.180443,"backgroundColor":"#FFFFFF","strokeColor":"#9CF394","label":{"text":"25%\r\n达成1:旗舰为战巡\r\n\n击破:-0J:开启","fontSize":12,"strokeColor":"#000000"},"id":"70412:70411"},{"start":{"id":"70412"},"end":{"id":"70414"},"type":"arrow","endArrowhead":"triangle","x":436.8082,"y":574.96747,"width":-188.6164,"height":-214.93498,"backgroundColor":"#FFFFFF","strokeColor":"#9CF394","label":{"text":"75%\r\n","fontSize":12,"strokeColor":"#000000"},"id":"70412:70414"},{"start":{"id":"70413"},"end":{"id":"70409"},"type":"arrow","endArrowhead":"triangle","x":416.87323,"y":334.26248,"width":76.25354,"height":-48.52498,"backgroundColor":"#FFFFFF","strokeColor":"#94F8F3","label":{"text":"60%\r\n","fontSize":12,"strokeColor":"#000000"},"id":"70413:70409"},{"start":{"id":"70413"},"end":{"id":"70414"},"type":"arrow","endArrowhead":"triangle","x":380,"y":345,"width":-125,"backgroundColor":"#FFFFFF","strokeColor":"#94F8F3","label":{"text":"40%\r\n达成1:战列≥2\r\n","fontSize":12,"strokeColor":"#000000"},"id":"70413:70414"},{"start":{"id":"70409"},"end":{"id":"70414"},"type":"arrow","endArrowhead":"triangle","x":490.61804,"y":279.9336,"width":-236.23611,"height":60.132828,"backgroundColor":"#FFFFFF","strokeColor":"#A1F394","label":{"text":"","fontSize":12,"strokeColor":"#000000"},"id":"70409:70414"},{"start":{"id":"70407"},"end":{"id":"70410"},"type":"arrow","endArrowhead":"triangle","x":785.5317,"y":709.5808,"width":-131.06331,"height":30.838427,"backgroundColor":"#FFFFFF","strokeColor":"#F294F3","label":{"text":"","fontSize":12,"strokeColor":"#000000"},"id":"70407:70410"},{"type":"ellipse","x":1025,"y":335,"width":40,"height":40,"backgroundColor":"#FFFFFF","label":{"text":"0","fontSize":16,"strokeColor":"#000000"},"id":"70401"},{"type":"ellipse","x":990,"y":485,"width":40,"height":40,"backgroundColor":"#ff9999","label":{"text":"A","fontSize":16,"strokeColor":"#000000"},"id":"70402"},{"type":"ellipse","x":900,"y":605,"width":40,"height":40,"backgroundColor":"#ff9999","label":{"text":"C","fontSize":16,"strokeColor":"#000000"},"id":"70404"},{"type":"ellipse","x":720,"y":415,"width":40,"height":40,"backgroundColor":"#ff9999","strokeColor":"#3377ff","label":{"text":"D","fontSize":16,"strokeColor":"#000000"},"id":"70405"},{"type":"ellipse","x":890,"y":235,"width":40,"height":40,"backgroundColor":"#ff9999","label":{"text":"B","fontSize":16,"strokeColor":"#000000"},"id":"70403"},{"type":"ellipse","x":645,"y":275,"width":40,"height":40,"backgroundColor":"#ff9999","label":{"text":"E","fontSize":16,"strokeColor":"#000000"},"id":"70406"},{"type":"rectangle","x":535,"y":410,"width":40,"height":40,"backgroundColor":"#66ff33","label":{"text":"G","fontSize":16,"strokeColor":"#000000"},"id":"70408"},{"type":"ellipse","x":430,"y":570,"width":40,"height":40,"backgroundColor":"#ff9999","label":{"text":"K","fontSize":16,"strokeColor":"#000000"},"id":"70412"},{"type":"ellipse","x":490,"y":665,"width":40,"height":40,"backgroundColor":"#ff9999","label":{"text":"J","fontSize":16,"strokeColor":"#000000"},"id":"70411"},{"type":"diamond","x":215,"y":325,"width":40,"height":40,"backgroundColor":"#FF3333","label":{"text":"M","fontSize":16,"strokeColor":"#000000"},"id":"70414"},{"type":"ellipse","x":380,"y":325,"width":40,"height":40,"backgroundColor":"#ff9999","strokeColor":"#3377ff","label":{"text":"L","fontSize":16,"strokeColor":"#000000"},"id":"70413"},{"type":"rectangle","x":490,"y":255,"width":40,"height":40,"backgroundColor":"#66ff33","label":{"text":"H","fontSize":16,"strokeColor":"#000000"},"id":"70409"},{"type":"ellipse","x":785,"y":685,"width":40,"height":40,"backgroundColor":"#ff9999","label":{"text":"F","fontSize":16,"strokeColor":"#000000"},"id":"70407"},{"type":"ellipse","x":615,"y":725,"width":40,"height":40,"backgroundColor":"#ff9999","label":{"text":"I","fontSize":16,"strokeColor":"#000000"},"id":"70410"}]